tools/__init__.py
tools/plotting.py
tools/remap.py
tools/vec3.py
tools/illustris_python/__init__.py
tools/illustris_python/groupcat.py
tools/illustris_python/lhalotree.py
tools/illustris_python/snapshot.py
tools/illustris_python/sublink.py
tools/illustris_python/util.py
tools/illustris_python/tests/__init__.py
tools/illustris_python/tests/__main__.py
tools/illustris_python/tests/groupcat_test.py
tools/illustris_python/tests/snapshot_test.py
tools/illustris_python/tests/sublink_test.py
light_gen-0.0.12.dist-info/LICENSE
light_gen-0.0.12.dist-info/METADATA
light_gen-0.0.12.dist-info/WHEEL
light_gen-0.0.12.dist-info/top_level.txt
light_gen-0.0.12.dist-info/RECORD
