Metadata-Version: 2.1
Name: light-gen
Version: 0.0.12
Summary: Generating lightcones from IllustrisTNG simulations
Home-page: https://github.com/SoumyaShreeram/LightGen
Author: SoumyaShreeram
Author-email: shreeramsoumya@gmail.com
License: MIT
Classifier: License :: OSI Approved :: MIT License
Classifier: Programming Language :: Python :: 3.10
Classifier: Operating System :: OS Independent
Requires-Python: >=3.9
License-File: LICENSE
Requires-Dist: astropy >=5.2.2
Requires-Dist: seaborn >=0.12.2
Requires-Dist: numpy >=1.24.3
Requires-Dist: scipy >=1.10.1
Requires-Dist: h5py >=3.10.0
Requires-Dist: pandas >=2.0.1
Provides-Extra: dev
Requires-Dist: pytest >=7.0 ; extra == 'dev'
Requires-Dist: twine >=4.0.2 ; extra == 'dev'
